py_report_html/__init__.py
py_report_html/cli_manager.py
py_report_html/py_report_html.py
py_report_html/js/ElGrapho.min.js
py_report_html/js/PyvisUtils.js
py_report_html/js/canvasXpress.css
py_report_html/js/canvasXpress.min.js
py_report_html/js/canvasXpress_license
py_report_html/js/cytoscape.min.js
py_report_html/js/mermaid.css
py_report_html/js/pako.min.js
py_report_html/js/py_report_html.css
py_report_html/js/py_report_html.js
py_report_html/templates/cytoscape.txt
py_report_html/templates/elgrapho.txt
py_report_html/templates/pyvis.txt
py_report_html/templates/sigma.txt
py_report_html/templates/sigma_cdn.txt
py_report_html/templates/table.txt
py_report_html-1.1.1.dist-info/LICENSE.txt
py_report_html-1.1.1.dist-info/METADATA
py_report_html-1.1.1.dist-info/WHEEL
py_report_html-1.1.1.dist-info/entry_points.txt
py_report_html-1.1.1.dist-info/top_level.txt
py_report_html-1.1.1.dist-info/RECORD
