Metadata-Version: 2.1
Name: py_report_html
Version: 1.1.1
Summary: Create compressed, interactive HTML reports with embedded Python code, custom JS and CSS, and wrappers for CanvasXpress plots, networks and more.
Home-page: https://github.com/seoanezonjic/py_report_html
Author: seoanezonjic
Author-email: seoanezonjic@uma.es
License: MIT
Project-URL: Documentation, https://github.com/seoanezonjic/py_report_html
Platform: any
Classifier: Development Status :: 4 - Beta
Classifier: Programming Language :: Python
License-File: LICENSE.txt
Requires-Dist: networkx
Requires-Dist: matplotlib
Requires-Dist: pandas
Requires-Dist: mako
Requires-Dist: seaborn
Requires-Dist: importlib-metadata ; python_version < "3.8"
Provides-Extra: testing
Requires-Dist: setuptools ; extra == 'testing'
Requires-Dist: pytest ; extra == 'testing'
Requires-Dist: pytest-cov ; extra == 'testing'
